Metadata-Version: 1.0
Name: jaja-probability-dsnd
Version: 0.1
Summary: Gaussian & binomial distributions
Home-page: UNKNOWN
Author: Tamuno-omi Jaja
Author-email: UNKNOWN
License: UNKNOWN
Platform: UNKNOWN
